<ImportMXDLog>	<Messages>
		<FileName>D:\CourseraGISLocal\NAD1019-Fundamentals of GIS\3_demo_documents\NAD1019-L5.3-Data Frames.mxd</FileName>
		<Message>
			<Name></Name>
			<MessageType>Warning</MessageType>
			<Severity>High</Severity>
			<Description>Basemap Layers cannot be published directly to a service</Description>
			<Code>00037</Code>
			<ComponentName>Reference</ComponentName>
			<ComponentType>Layer</ComponentType>
</Message>
		<Message>
			<Name></Name>
			<MessageType>Error</MessageType>
			<Severity>High</Severity>
			<Description>Layer&apos;s data source is inaccessible</Description>
			<Code>00003</Code>
			<ComponentName>NHDFlowline</ComponentName>
			<ComponentType>Layer</ComponentType>
</Message>
		<Message>
			<Name></Name>
			<MessageType>Warning</MessageType>
			<Severity>High</Severity>
			<Description>Basemap Layers cannot be published directly to a service</Description>
			<Code>00037</Code>
			<ComponentName>Basemap</ComponentName>
			<ComponentType>Layer</ComponentType>
</Message>
		<Message>
			<Name></Name>
			<MessageType>Warning</MessageType>
			<Severity>Medium</Severity>
			<Description>Due to the differences between mxds and projects, some dynamic text tags may have changed during the import process.</Description>
			<Code>20044</Code>
			<ComponentName>NAD1019-L5.3-Data Frames</ComponentName>
			<ComponentType>Layout</ComponentType>
</Message>
</Messages>
</ImportMXDLog>