<ImportMXDLog>	<Messages>
		<FileName>D:\CourseraGISLocal\NAD1019-Fundamentals of GIS\3_demo_documents\NAD1019-L7.4-MapPackages.mxd</FileName>
		<Message>
			<Name></Name>
			<MessageType>Error</MessageType>
			<Severity>High</Severity>
			<Description>Layer&apos;s data source is inaccessible</Description>
			<Code>00003</Code>
			<ComponentName>Historical Range - Expert Opinion</ComponentName>
			<ComponentType>Layer</ComponentType>
</Message>
		<Message>
			<Name></Name>
			<MessageType>Error</MessageType>
			<Severity>High</Severity>
			<Description>Layer&apos;s data source is inaccessible</Description>
			<Code>00003</Code>
			<ComponentName>Observed</ComponentName>
			<ComponentType>Layer</ComponentType>
</Message>
		<Message>
			<Name></Name>
			<MessageType>Error</MessageType>
			<Severity>High</Severity>
			<Description>Layer&apos;s data source is inaccessible</Description>
			<Code>00003</Code>
			<ComponentName>Extant Range - Expert Opinion</ComponentName>
			<ComponentType>Layer</ComponentType>
</Message>
		<Message>
			<Name></Name>
			<MessageType>Warning</MessageType>
			<Severity>Medium</Severity>
			<Description>Layer uses symbol level drawing with a non-simple fill symbol</Description>
			<Code>10019</Code>
			<ComponentName>Extant Range - Expert Opinion</ComponentName>
			<ComponentType>Layer</ComponentType>
</Message>
		<Message>
			<Name></Name>
			<MessageType>Warning</MessageType>
			<Severity>Medium</Severity>
			<Description>Layer uses symbol level drawing with a non-simple fill symbol</Description>
			<Code>10019</Code>
			<ComponentName>Extant Range - Expert Opinion</ComponentName>
			<ComponentType>Layer</ComponentType>
</Message>
		<Message>
			<Name></Name>
			<MessageType>Warning</MessageType>
			<Severity>Medium</Severity>
			<Description>Layer uses symbol level drawing with a non-simple fill symbol</Description>
			<Code>10019</Code>
			<ComponentName>Extant Range - Expert Opinion</ComponentName>
			<ComponentType>Layer</ComponentType>
</Message>
		<Message>
			<Name></Name>
			<MessageType>Warning</MessageType>
			<Severity>Medium</Severity>
			<Description>Layer uses symbol level drawing with a non-simple fill symbol</Description>
			<Code>10019</Code>
			<ComponentName>Extant Range - Expert Opinion</ComponentName>
			<ComponentType>Layer</ComponentType>
</Message>
		<Message>
			<Name></Name>
			<MessageType>Warning</MessageType>
			<Severity>Medium</Severity>
			<Description>Layer uses symbol level drawing with a non-simple fill symbol</Description>
			<Code>10019</Code>
			<ComponentName>Extant Range - Expert Opinion</ComponentName>
			<ComponentType>Layer</ComponentType>
</Message>
		<Message>
			<Name></Name>
			<MessageType>Warning</MessageType>
			<Severity>Medium</Severity>
			<Description>Scales for maps on the layout may not have imported correctly.</Description>
			<Code>20037</Code>
			<ComponentName>NAD1019-L7.4-MapPackages</ComponentName>
			<ComponentType>Layout</ComponentType>
</Message>
</Messages>
</ImportMXDLog>